MANIFEST.in
README.rst
setup.py
bChart/__init__.py
bChart/bchart.py
bChart.egg-info/PKG-INFO
bChart.egg-info/SOURCES.txt
bChart.egg-info/dependency_links.txt
bChart.egg-info/top_level.txt
bChart.egg-info/zip-safe
bchart/__init__.py
bchart/bchart.py
bchart.egg-info/SOURCES.txt