Metadata-Version: 1.1
Name: bchart
Version: 0.1.1
Summary: A Python script for bChart
Home-page: https://github.com/jessemao/bChart-python
Author: Jingxian Mao
Author-email: jessemao@gmail.com
License: MIT License
Keywords: data visualization,bChart,d3
Platform: UNKNOWN
Classifier: Development Status :: 4 - Beta
Classifier: Programming Language :: Python :: 2.7
Classifier: License :: OSI Approved :: MIT License
